pipeline_functions/__init__.py
pipeline_functions/logger.py
pipeline_functions/exceptions/__init__.py
test/__init__.py
test/fixtures.py
test/test_pipeline_functions.py
pipeline_functions-0.0.1.dist-info/LICENSE
pipeline_functions-0.0.1.dist-info/METADATA
pipeline_functions-0.0.1.dist-info/WHEEL
pipeline_functions-0.0.1.dist-info/top_level.txt
pipeline_functions-0.0.1.dist-info/RECORD
