Metadata-Version: 2.1
Name: pipeline_functions
Version: 0.0.1
Summary: Class for manipulating a pipeline of functions, creating chains of functions processing the same context
Home-page: https://github.com/xxpauloxx/pipeline-functions
Author: Paulo Roberto
Author-email: paulo.pinda@gmail.com
License: GPLv3+
Project-URL: Bug Tracker, https://github.com/xxpauloxx/pipeline-functions/issues
Platform: UNKNOWN
Classifier: Programming Language :: Python :: 3
Classifier: License :: OSI Approved :: MIT License
Classifier: Operating System :: OS Independent
Requires-Python: >=3.6
License-File: LICENSE
